gradio_agent_inspector/__init__.py
gradio_agent_inspector/agent_inspector.py
gradio_agent_inspector/agent_inspector.pyi
gradio_agent_inspector/templates/component/index.js
gradio_agent_inspector/templates/component/style.css
gradio_agent_inspector/templates/example/index.js
gradio_agent_inspector/templates/example/style.css
gradio_agent_inspector-0.0.2.dist-info/METADATA
gradio_agent_inspector-0.0.2.dist-info/WHEEL
gradio_agent_inspector-0.0.2.dist-info/RECORD
