Metadata-Version: 2.4
Name: gradio_agent_inspector
Version: 0.0.2
Summary: Agent Inspector for ADK
Author: Francois Lancelot
License-Expression: Apache-2.0
Keywords: adk,agent,custom-component-track,gradio-custom-component,llm,tools
Classifier: Development Status :: 3 - Alpha
Classifier: Operating System :: OS Independent
Classifier: Programming Language :: Python :: 3
Classifier: Programming Language :: Python :: 3 :: Only
Classifier: Programming Language :: Python :: 3.8
Classifier: Programming Language :: Python :: 3.9
Classifier: Programming Language :: Python :: 3.10
Classifier: Programming Language :: Python :: 3.11
Classifier: Topic :: Scientific/Engineering
Classifier: Topic :: Scientific/Engineering :: Artificial Intelligence
Classifier: Topic :: Scientific/Engineering :: Visualization
Requires-Python: >=3.10
Requires-Dist: gradio<6.0,>=4.0
Provides-Extra: dev
Requires-Dist: build; extra == 'dev'
Requires-Dist: twine; extra == 'dev'
